nshuman/__init__.py
nshuman/data/__init__.py
nshuman/data/coco_tools.py
nshuman/data/image.py
nshuman/data/json_utils.py
nshuman/eval/__init__.py
nshuman/eval/coco.py
nshuman/eval/mot.py
nshuman/eval/mot_evaluator_custom.py
nshuman/human/__init__.py
nshuman/human/common.py
nshuman/human/get_result.py
nshuman/model_zoo/__init__.py
nshuman/model_zoo/get_models.py
nshuman/model_zoo/model_attribute/__init__.py
nshuman/model_zoo/model_attribute/gender.py
nshuman/model_zoo/model_common/__init__.py
nshuman/model_zoo/model_common/load_onnx.py
nshuman/model_zoo/model_common/load_openvino.py
nshuman/model_zoo/model_common/load_tensorRT.py
nshuman/model_zoo/model_common/load_tensorRT_multiple.py
nshuman/model_zoo/model_detection/__init__.py
nshuman/model_zoo/model_detection/yolov5.py
nshuman/model_zoo/model_detection/yolov7.py
nshuman/model_zoo/model_detection/yolox.py
nshuman/model_zoo/model_pose/__init__.py
nshuman/model_zoo/model_pose/vitpose.py
nshuman/model_zoo/model_tracker/__init__.py
nshuman/model_zoo/model_tracker/bytetracker.py
nshuman/model_zoo/model_tracker/bytetrack/__init__.py
nshuman/model_zoo/model_tracker/bytetrack/dist.py
nshuman/model_zoo/model_tracker/bytetrack/visualize.py
nshuman/model_zoo/model_tracker/bytetrack/tracker/__init__.py
nshuman/model_zoo/model_tracker/bytetrack/tracker/basetrack.py
nshuman/model_zoo/model_tracker/bytetrack/tracker/byte_tracker.py
nshuman/model_zoo/model_tracker/bytetrack/tracker/kalman_filter.py
nshuman/model_zoo/model_tracker/bytetrack/tracker/matching.py
nshuman/model_zoo/model_tracker/bytetrack/tracking_utils/__init__.py
nshuman/model_zoo/model_tracker/bytetrack/tracking_utils/io.py
nshuman/model_zoo/model_tracker/bytetrack/tracking_utils/timer.py
nshuman/utils/__init__.py
nshuman/utils/utils_attribute/__init__.py
nshuman/utils/utils_attribute/gender_util.py
nshuman/utils/utils_detection/__init__.py
nshuman/utils/utils_detection/draw_result.py
nshuman/utils/utils_detection/yolo_const.py
nshuman_python-0.0.8.dist-info/METADATA
nshuman_python-0.0.8.dist-info/WHEEL
nshuman_python-0.0.8.dist-info/top_level.txt
nshuman_python-0.0.8.dist-info/RECORD
