Metadata-Version: 2.1
Name: nshuman-python
Version: 0.0.8
Summary: nshuman gpu package
Home-page: UNKNOWN
Author: minsuny
Author-email: minsun.y@nsensecorp.com
License: UNKNOWN
Platform: UNKNOWN
Requires-Python: >=3
Requires-Dist: tqdm
Requires-Dist: loguru
Requires-Dist: lap
Requires-Dist: cython-bbox
Requires-Dist: easydict
Requires-Dist: motmetrics
